pykitml/__init__.py
pykitml/_classifier.py
pykitml/_exceptions.py
pykitml/_functions.py
pykitml/_heatmap.py
pykitml/_minimize_model.py
pykitml/_regressor.py
pykitml/_shared_array.py
pykitml/_single_layer_model.py
pykitml/cross_val.py
pykitml/decision_tree.py
pykitml/dqn.py
pykitml/fceux.py
pykitml/kmeans_clustering.py
pykitml/linear_regression.py
pykitml/logistic_regression.py
pykitml/lstm.py
pykitml/naive_bayes.py
pykitml/nearest_neighbor.py
pykitml/network.py
pykitml/normalize.py
pykitml/optimizers.py
pykitml/pca.py
pykitml/pklhandler.py
pykitml/preprocessing.py
pykitml/random_forest.py
pykitml/random_search.py
pykitml/smote.py
pykitml/svm.py
pykitml/testing.py
pykitml/datasets/__init__.py
pykitml/datasets/_s1_compressed.py
pykitml/datasets/adult.py
pykitml/datasets/banknote.py
pykitml/datasets/boston.py
pykitml/datasets/fishlength.py
pykitml/datasets/heartdisease.py
pykitml/datasets/iris.py
pykitml/datasets/mnist.py
pykitml/datasets/s1clustering.py
pykitml/datasets/sonar.py
pykitml-0.1.3.dist-info/LICENSE
pykitml-0.1.3.dist-info/METADATA
pykitml-0.1.3.dist-info/WHEEL
pykitml-0.1.3.dist-info/top_level.txt
pykitml-0.1.3.dist-info/RECORD
