Metadata-Version: 2.1
Name: pykitml
Version: 0.1.3
Summary: Machine Learning library written in Python and NumPy.
Home-page: https://github.com/RainingComputers/pykitml
Author: RainingComputers
Author-email: vishnu.vish.shankar@gmail.com
Keywords: pykitml
Classifier: Programming Language :: Python :: 3
Classifier: License :: OSI Approved :: MIT License
Classifier: Operating System :: OS Independent
Classifier: Development Status :: 3 - Alpha
Classifier: Topic :: Scientific/Engineering :: Artificial Intelligence
Requires-Python: >=3.10
License-File: LICENSE
Requires-Dist: numpy
Requires-Dist: matplotlib
Requires-Dist: tqdm
Requires-Dist: graphviz
